LICENSE.txt.
README.md
setup.py
MMetaTrader5/__init__.py
MMetaTrader5.egg-info/PKG-INFO
MMetaTrader5.egg-info/SOURCES.txt
MMetaTrader5.egg-info/dependency_links.txt
MMetaTrader5.egg-info/requires.txt
MMetaTrader5.egg-info/top_level.txt