Metadata-Version: 2.4
Name: MMetaTrader5
Version: 0.0.1
Summary: Metatrader5 mock for Mac developers
Home-page: https://github.com/jgonzmoya/m_metatrader_5
Author: Javier Gonzalez Moya
Author-email: javigonzmoya@gmail.com
License: MIT
Classifier: Development Status :: 3 - Alpha
Classifier: Intended Audience :: Developers
Classifier: Topic :: Software Development :: Build Tools
Classifier: License :: OSI Approved :: MIT License
Classifier: Programming Language :: Python :: 3
License-File: LICENSE.txt.
Requires-Dist: numpy
Dynamic: author
Dynamic: author-email
Dynamic: classifier
Dynamic: description
Dynamic: description-content-type
Dynamic: home-page
Dynamic: license
Dynamic: license-file
Dynamic: requires-dist
Dynamic: summary
